oauth_valid/__init__.py
oauth_valid/facebook.py
oauth_valid/google.py
oauth_valid/kakao.py
oauth_valid-0.2.3.dist-info/METADATA
oauth_valid-0.2.3.dist-info/WHEEL
oauth_valid-0.2.3.dist-info/top_level.txt
oauth_valid-0.2.3.dist-info/RECORD
