Metadata-Version: 2.1
Name: oauth-valid
Version: 0.2.3
Summary: oauth valid and it serve some utility
Home-page: https://github.com/zaeval/oauth-valid
Author: zaeval
Author-email: zaeval@among.software
License: UNKNOWN
Platform: UNKNOWN
Classifier: Programming Language :: Python :: 3
Classifier: License :: OSI Approved :: MIT License
Classifier: Operating System :: OS Independent
Requires-Dist: requests
Requires-Dist: bs4
